muvius/__init__.py
muvius/cli.py
muvius-0.2.1.dist-info/licenses/LICENSE
muvius-0.2.1.dist-info/METADATA
muvius-0.2.1.dist-info/WHEEL
muvius-0.2.1.dist-info/entry_points.txt
muvius-0.2.1.dist-info/top_level.txt
muvius-0.2.1.dist-info/RECORD
